{
    "ID": 1262,
    "post_title": "women-empowerment-02.jpg",
    "post_name": "women-empowerment-02-jpg",
    "post_date": "2025-02-06 11:12:11",
    "post_mime_type": "image\/jpeg",
    "filename": "women-empowerment-02-scaled.jpg",
    "meta": {
        "_wp_attached_file": [
            "2025\/02\/women-empowerment-02-scaled.jpg"
        ],
        "_wp_attachment_metadata": [
            {
                "width": 532,
                "height": 2560,
                "file": "2025\/02\/women-empowerment-02-scaled.jpg",
                "filesize": 156492,
                "sizes": {
                    "medium": {
                        "file": "women-empowerment-02-62x300.jpg",
                        "width": 62,
                        "height": 300,
                        "mime-type": "image\/jpeg",
                        "filesize": 4873
                    },
                    "large": {
                        "file": "women-empowerment-02-213x1024.jpg",
                        "width": 213,
                        "height": 1024,
                        "mime-type": "image\/jpeg",
                        "filesize": 34851
                    },
                    "thumbnail": {
                        "file": "women-empowerment-02-150x150.jpg",
                        "width": 150,
                        "height": 150,
                        "mime-type": "image\/jpeg",
                        "filesize": 4169
                    },
                    "medium_large": {
                        "file": "women-empowerment-02-768x3699.jpg",
                        "width": 768,
                        "height": 3699,
                        "mime-type": "image\/jpeg",
                        "filesize": 278500
                    },
                    "1536x1536": {
                        "file": "women-empowerment-02-319x1536.jpg",
                        "width": 319,
                        "height": 1536,
                        "mime-type": "image\/jpeg",
                        "filesize": 67456
                    },
                    "2048x2048": {
                        "file": "women-empowerment-02-425x2048.jpg",
                        "width": 425,
                        "height": 2048,
                        "mime-type": "image\/jpeg",
                        "filesize": 107154
                    }
                },
                "image_meta": {
                    "aperture": "0",
                    "credit": "",
                    "camera": "",
                    "caption": "",
                    "created_timestamp": "0",
                    "copyright": "",
                    "focal_length": "0",
                    "iso": "0",
                    "shutter_speed": "0",
                    "title": "",
                    "orientation": "0",
                    "keywords": []
                },
                "original_image": "women-empowerment-02.jpg"
            }
        ],
        "_astra_portfolio_image_hash": [
            "61c7a7eba9d91a93c6799c4e41b4e894b8b902cb"
        ]
    }
}