{
    "ID": 329,
    "post_title": "heritage-hotel-07.jpg",
    "post_name": "heritage-hotel-07-jpg",
    "post_date": "2025-02-06 11:01:11",
    "post_mime_type": "image\/jpeg",
    "filename": "heritage-hotel-07-scaled.jpg",
    "meta": {
        "_wp_attached_file": [
            "2025\/02\/heritage-hotel-07-scaled.jpg"
        ],
        "_wp_attachment_metadata": [
            {
                "width": 336,
                "height": 2560,
                "file": "2025\/02\/heritage-hotel-07-scaled.jpg",
                "filesize": 181507,
                "sizes": {
                    "medium": {
                        "file": "heritage-hotel-07-39x300.jpg",
                        "width": 39,
                        "height": 300,
                        "mime-type": "image\/jpeg",
                        "filesize": 5957
                    },
                    "large": {
                        "file": "heritage-hotel-07-134x1024.jpg",
                        "width": 134,
                        "height": 1024,
                        "mime-type": "image\/jpeg",
                        "filesize": 39061
                    },
                    "thumbnail": {
                        "file": "heritage-hotel-07-150x150.jpg",
                        "width": 150,
                        "height": 150,
                        "mime-type": "image\/jpeg",
                        "filesize": 7526
                    },
                    "medium_large": {
                        "file": "heritage-hotel-07-768x5852.jpg",
                        "width": 768,
                        "height": 5852,
                        "mime-type": "image\/jpeg",
                        "filesize": 746520
                    },
                    "1536x1536": {
                        "file": "heritage-hotel-07-202x1536.jpg",
                        "width": 202,
                        "height": 1536,
                        "mime-type": "image\/jpeg",
                        "filesize": 77702
                    },
                    "2048x2048": {
                        "file": "heritage-hotel-07-269x2048.jpg",
                        "width": 269,
                        "height": 2048,
                        "mime-type": "image\/jpeg",
                        "filesize": 126328
                    }
                },
                "image_meta": {
                    "aperture": "0",
                    "credit": "",
                    "camera": "",
                    "caption": "",
                    "created_timestamp": "0",
                    "copyright": "",
                    "focal_length": "0",
                    "iso": "0",
                    "shutter_speed": "0",
                    "title": "",
                    "orientation": "0",
                    "keywords": []
                },
                "original_image": "heritage-hotel-07.jpg"
            }
        ],
        "_astra_portfolio_image_hash": [
            "62500e6a843474c944bb980cf29e32576c53f273"
        ]
    }
}