{
    "ID": 462,
    "post_title": "app-landing-page-07.jpg",
    "post_name": "app-landing-page-07-jpg",
    "post_date": "2025-02-06 11:03:32",
    "post_mime_type": "image\/jpeg",
    "filename": "app-landing-page-07-scaled.jpg",
    "meta": {
        "_wp_attached_file": [
            "2025\/02\/app-landing-page-07-scaled.jpg"
        ],
        "_wp_attachment_metadata": [
            {
                "width": 456,
                "height": 2560,
                "file": "2025\/02\/app-landing-page-07-scaled.jpg",
                "filesize": 179539,
                "sizes": {
                    "medium": {
                        "file": "app-landing-page-07-53x300.jpg",
                        "width": 53,
                        "height": 300,
                        "mime-type": "image\/jpeg",
                        "filesize": 6919
                    },
                    "large": {
                        "file": "app-landing-page-07-182x1024.jpg",
                        "width": 182,
                        "height": 1024,
                        "mime-type": "image\/jpeg",
                        "filesize": 42054
                    },
                    "thumbnail": {
                        "file": "app-landing-page-07-150x150.jpg",
                        "width": 150,
                        "height": 150,
                        "mime-type": "image\/jpeg",
                        "filesize": 7301
                    },
                    "medium_large": {
                        "file": "app-landing-page-07-768x4314.jpg",
                        "width": 768,
                        "height": 4314,
                        "mime-type": "image\/jpeg",
                        "filesize": 421383
                    },
                    "1536x1536": {
                        "file": "app-landing-page-07-273x1536.jpg",
                        "width": 273,
                        "height": 1536,
                        "mime-type": "image\/jpeg",
                        "filesize": 79314
                    },
                    "2048x2048": {
                        "file": "app-landing-page-07-365x2048.jpg",
                        "width": 365,
                        "height": 2048,
                        "mime-type": "image\/jpeg",
                        "filesize": 128072
                    }
                },
                "image_meta": {
                    "aperture": "0",
                    "credit": "",
                    "camera": "",
                    "caption": "",
                    "created_timestamp": "0",
                    "copyright": "",
                    "focal_length": "0",
                    "iso": "0",
                    "shutter_speed": "0",
                    "title": "",
                    "orientation": "0",
                    "keywords": []
                },
                "original_image": "app-landing-page-07.jpg"
            }
        ],
        "_astra_portfolio_image_hash": [
            "dd2012accdc045880bb471462255addc1eb0de12"
        ]
    }
}