{
    "ID": 533,
    "post_title": "author-07.jpg",
    "post_name": "author-07-jpg-2",
    "post_date": "2025-02-06 11:04:09",
    "post_mime_type": "image\/jpeg",
    "filename": "author-07-1-scaled.jpg",
    "meta": {
        "_wp_attached_file": [
            "2025\/02\/author-07-1-scaled.jpg"
        ],
        "_wp_attachment_metadata": [
            {
                "width": 791,
                "height": 2560,
                "file": "2025\/02\/author-07-1-scaled.jpg",
                "filesize": 208315,
                "sizes": {
                    "medium": {
                        "file": "author-07-1-93x300.jpg",
                        "width": 93,
                        "height": 300,
                        "mime-type": "image\/jpeg",
                        "filesize": 7846
                    },
                    "large": {
                        "file": "author-07-1-316x1024.jpg",
                        "width": 316,
                        "height": 1024,
                        "mime-type": "image\/jpeg",
                        "filesize": 45582
                    },
                    "thumbnail": {
                        "file": "author-07-1-150x150.jpg",
                        "width": 150,
                        "height": 150,
                        "mime-type": "image\/jpeg",
                        "filesize": 5653
                    },
                    "medium_large": {
                        "file": "author-07-1-768x2486.jpg",
                        "width": 768,
                        "height": 2486,
                        "mime-type": "image\/jpeg",
                        "filesize": 197970
                    },
                    "1536x1536": {
                        "file": "author-07-1-474x1536.jpg",
                        "width": 474,
                        "height": 1536,
                        "mime-type": "image\/jpeg",
                        "filesize": 87996
                    },
                    "2048x2048": {
                        "file": "author-07-1-633x2048.jpg",
                        "width": 633,
                        "height": 2048,
                        "mime-type": "image\/jpeg",
                        "filesize": 145792
                    }
                },
                "image_meta": {
                    "aperture": "0",
                    "credit": "",
                    "camera": "",
                    "caption": "",
                    "created_timestamp": "0",
                    "copyright": "",
                    "focal_length": "0",
                    "iso": "0",
                    "shutter_speed": "0",
                    "title": "",
                    "orientation": "0",
                    "keywords": []
                },
                "original_image": "author-07-1.jpg"
            }
        ],
        "_astra_portfolio_image_hash": [
            "1bdb718bd17b9de68f7e012ce0e4c721e1678eff"
        ]
    }
}