{
    "ID": 589,
    "post_title": "personals-trainer-07.jpg",
    "post_name": "personals-trainer-07-jpg",
    "post_date": "2025-02-06 11:04:42",
    "post_mime_type": "image\/jpeg",
    "filename": "personals-trainer-07-scaled.jpg",
    "meta": {
        "_wp_attached_file": [
            "2025\/02\/personals-trainer-07-scaled.jpg"
        ],
        "_wp_attachment_metadata": [
            {
                "width": 469,
                "height": 2560,
                "file": "2025\/02\/personals-trainer-07-scaled.jpg",
                "filesize": 189547,
                "sizes": {
                    "medium": {
                        "file": "personals-trainer-07-55x300.jpg",
                        "width": 55,
                        "height": 300,
                        "mime-type": "image\/jpeg",
                        "filesize": 6508
                    },
                    "large": {
                        "file": "personals-trainer-07-187x1024.jpg",
                        "width": 187,
                        "height": 1024,
                        "mime-type": "image\/jpeg",
                        "filesize": 41938
                    },
                    "thumbnail": {
                        "file": "personals-trainer-07-150x150.jpg",
                        "width": 150,
                        "height": 150,
                        "mime-type": "image\/jpeg",
                        "filesize": 4623
                    },
                    "medium_large": {
                        "file": "personals-trainer-07-768x4195.jpg",
                        "width": 768,
                        "height": 4195,
                        "mime-type": "image\/jpeg",
                        "filesize": 414991
                    },
                    "1536x1536": {
                        "file": "personals-trainer-07-281x1536.jpg",
                        "width": 281,
                        "height": 1536,
                        "mime-type": "image\/jpeg",
                        "filesize": 80336
                    },
                    "2048x2048": {
                        "file": "personals-trainer-07-375x2048.jpg",
                        "width": 375,
                        "height": 2048,
                        "mime-type": "image\/jpeg",
                        "filesize": 128628
                    }
                },
                "image_meta": {
                    "aperture": "0",
                    "credit": "",
                    "camera": "",
                    "caption": "",
                    "created_timestamp": "0",
                    "copyright": "",
                    "focal_length": "0",
                    "iso": "0",
                    "shutter_speed": "0",
                    "title": "",
                    "orientation": "0",
                    "keywords": []
                },
                "original_image": "personals-trainer-07.jpg"
            }
        ],
        "_astra_portfolio_image_hash": [
            "4f3ba7323cebd990213f74a15e24c3b514f92af1"
        ]
    }
}